estherandthai/__init__.py
estherandthai/app.py
estherandthai/message.py
estherandthai/time_machine.py
estherandthai/static/style.css
estherandthai/templates/base.html
estherandthai/templates/tm/base.html
estherandthai/templates/tm/context.html
estherandthai/templates/tm/date.html
estherandthai/templates/tm/date_results.html
estherandthai/templates/tm/empty.html
estherandthai/templates/tm/index.html
estherandthai/templates/tm/message.html
estherandthai/templates/tm/message_results.html
estherandthai/templates/tm/results.html
estherandthai/templates/tm/search.html
estherandthai-0.0.1.dist-info/METADATA
estherandthai-0.0.1.dist-info/WHEEL
estherandthai-0.0.1.dist-info/licenses/LICENSE.md
estherandthai-0.0.1.dist-info/RECORD
